llvmcovdiff/__main__.py
llvmcovdiff/diff_line_coverage.py
llvmcovdiff/diff_main_report.py
llvmcovdiff/full_report_diff.py
llvmcovdiff-0.0.4.dist-info/METADATA
llvmcovdiff-0.0.4.dist-info/WHEEL
llvmcovdiff-0.0.4.dist-info/top_level.txt
llvmcovdiff-0.0.4.dist-info/RECORD
