Metadata-Version: 2.1
Name: llvmcovdiff
Version: 0.0.4
Summary: Compare two llvm-cov html coverage report.
Author-email: wjk <warrenwjk@qq.com>
Project-URL: Homepage, https://github.com/am009/llvm-cov-html-diff
Project-URL: Issues, https://github.com/am009/llvm-cov-html-diff/issues
Classifier: Programming Language :: Python :: 3
Classifier: License :: OSI Approved :: MIT License
Classifier: Operating System :: OS Independent
Requires-Python: >=3.8
Requires-Dist: beautifulsoup4
